allsort/__init__.py
allsort/sortall.py
tests/__init__.py
tests/tests_sortall.py
allsort-0.1.0.dist-info/LICENSE
allsort-0.1.0.dist-info/METADATA
allsort-0.1.0.dist-info/WHEEL
allsort-0.1.0.dist-info/top_level.txt
allsort-0.1.0.dist-info/RECORD
