Metadata-Version: 2.1
Name: allsort
Version: 0.1.0
Summary: A Python package for sorting dictionaries, lists, tuples, and sets.
Home-page: https://github.com/Amit145/allsort
Author: Amit Ghatge
Author-email: amitghatge37@gmail.com
License: MIT
Classifier: Programming Language :: Python :: 3
Classifier: License :: OSI Approved :: MIT License
Classifier: Operating System :: OS Independent
Requires-Python: >=3.6
License-File: LICENSE
